Metadata-Version: 2.1
Name: file-explorer
Version: 0.0.0
Summary: A simple python cli file browser
Home-page: https://github.com/WangTingZheng/explorer
Author: WangTingZheng
Author-email: wangtingzheng@outlook.com
License: UNKNOWN
Platform: UNKNOWN
